README
setup.py
torrentcheck.py
torrentcheck.egg-info/PKG-INFO
torrentcheck.egg-info/SOURCES.txt
torrentcheck.egg-info/dependency_links.txt
torrentcheck.egg-info/entry_points.txt
torrentcheck.egg-info/requires.txt
torrentcheck.egg-info/top_level.txt